aiida_workgraph/__init__.py
aiida_workgraph/collection.py
aiida_workgraph/config.py
aiida_workgraph/decorator.py
aiida_workgraph/manager.py
aiida_workgraph/property.py
aiida_workgraph/registry.py
aiida_workgraph/serialization.py
aiida_workgraph/socket.py
aiida_workgraph/socket_spec.py
aiida_workgraph/task.py
aiida_workgraph/workgraph.py
aiida_workgraph/cli/__init__.py
aiida_workgraph/cli/cmd_task.py
aiida_workgraph/cli/cmd_workgraph.py
aiida_workgraph/engine/__init__.py
aiida_workgraph/engine/awaitable_manager.py
aiida_workgraph/engine/context_manager.py
aiida_workgraph/engine/error_handler_manager.py
aiida_workgraph/engine/task_actions.py
aiida_workgraph/engine/task_manager.py
aiida_workgraph/engine/task_state.py
aiida_workgraph/engine/workgraph.py
aiida_workgraph/executors/__init__.py
aiida_workgraph/executors/builtins.py
aiida_workgraph/executors/test.py
aiida_workgraph/orm/__init__.py
aiida_workgraph/orm/mapping.py
aiida_workgraph/orm/utils.py
aiida_workgraph/orm/workgraph.py
aiida_workgraph/properties/__init__.py
aiida_workgraph/properties/builtins.py
aiida_workgraph/properties/property_pool.py
aiida_workgraph/schemas/__init__.py
aiida_workgraph/schemas/aiida_workgraph.schema.json
aiida_workgraph/sockets/__init__.py
aiida_workgraph/sockets/builtins.py
aiida_workgraph/sockets/socket_pool.py
aiida_workgraph/tasks/__init__.py
aiida_workgraph/tasks/aiida.py
aiida_workgraph/tasks/builtins.py
aiida_workgraph/tasks/function_task.py
aiida_workgraph/tasks/graph_task.py
aiida_workgraph/tasks/monitors.py
aiida_workgraph/tasks/pythonjob_tasks.py
aiida_workgraph/tasks/shelljob_task.py
aiida_workgraph/tasks/subgraph_task.py
aiida_workgraph/tasks/task_pool.py
aiida_workgraph/tasks/tests.py
aiida_workgraph/utils/__init__.py
aiida_workgraph/utils/control.py
aiida_workgraph/utils/logging.py
aiida_workgraph/utils/svg_to_html.py
aiida_workgraph-0.8.1.dist-info/entry_points.txt
aiida_workgraph-0.8.1.dist-info/licenses/LICENSE
aiida_workgraph-0.8.1.dist-info/WHEEL
aiida_workgraph-0.8.1.dist-info/METADATA
aiida_workgraph-0.8.1.dist-info/RECORD
